[
  {
    "name": "A perfect coffee",
    "cover": "/build/images/cover1.webp"
  },
  {
    "name": "Isaac's monster",
    "cover": "/build/images/cover2.webp"
  },
  {
    "name": "Pizza Stellar",
    "cover": "/build/images/cover3.webp"
  },
  {
    "name": "Scary monsters",
    "cover": "/build/images/cover4.webp"
  },
  {
    "name": "Remote work",
    "cover": "/build/images/cover5.webp"
  },
  {
    "name": "Design patters",
    "cover": "/build/images/cover6.webp"
  },
  {
    "name": "Preparing to migrate",
    "cover": "/build/images/cover7.webp"
  },
  {
    "name": "For the power of love",
    "cover": "/build/images/cover8.webp"
  }
]